04_tabla_POS/tabla04POS.v
module tabla04POS();

    reg A, B, C, D;
    wire w1, w2, w3, w4, w5, w6, w7, w8, w9, w10, w11, w12, w13, out;

    not U1(w1, A);
    not U2(w2, B);
    not U3(w3, C);
    not U4(w4, D);
    or   U5(w5, A, B, C, w4);
    or   U6(w6, A, w2, C, D);
    or   U7(w7, A, w2, C, w4);
    or   U8(w8, w1, B, C, w4);
    or   U9(w9, w1, B, w3, w4);
    or   U10(w10, w1, w2, C, D);
    or   U11(w11, w1, w2, C, w4);
    or   U12(w12, w1, w2, w3, D);
    or   U13(w13, w1, w2, w3, w4);
    and   U14(out, w5, w6, w7, w8, w9, w10, w11, w12, w13);

    initial begin
        $display("A B C D | Y");
        $display("-------------");
        $monitor("%b %b %b %b | %b", A, B, C, D, out);
        A = 0; B = 0; C = 0; D = 0;
        #1 D = 1;
        #1 C = 1; D = 0;
        #1 D = 1;
        #1 B = 1; C = 0; D = 0;
        #1 D = 1;
        #1 C = 1; D = 0;
        #1 D = 1;
        #1 A =1; B = 0; C = 0; D = 0;
        #1 D = 1;
        #1 C = 1; D = 0;
        #1 D = 1;
        #1 B = 1; C = 0; D = 0;
        #1 D = 1;
        #1 C = 1; D = 0;
        #1 D = 1;
        #1 $finish;
    end

    initial
      begin
        $dumpfile("tabla04POS_tb.vcd");
        $dumpvars(0, tabla04POS);
      end

endmodule

04_tabla_POS/tabla04POS_tb.vcd
$date
	Fri Jul 31 00:00:22 2020
$end
$version
	Icarus Verilog
$end
$timescale
	1ps
$end
$scope module tabla04POS $end
$var wire 1 ! out $end
$var wire 1 " w1 $end
$var wire 1 # w10 $end
$var wire 1 $ w11 $end
$var wire 1 % w12 $end
$var wire 1 & w13 $end
$var wire 1 ' w2 $end
$var wire 1 ( w3 $end
$var wire 1 ) w4 $end
$var wire 1 * w5 $end
$var wire 1 + w6 $end
$var wire 1 , w7 $end
$var wire 1 - w8 $end
$var wire 1 . w9 $end
$var reg 1 / A $end
$var reg 1 0 B $end
$var reg 1 1 C $end
$var reg 1 2 D $end
$upscope $end
$enddefinitions $end
#0
$dumpvars
02
01
00
0/
1.
1-
1,
1+
1*
1)
1(
1'
1&
1%
1$
1#
1"
1!
$end
#1
0!
0*
0)
12
#2
1!
1)
1*
0(
02
11
#3
0)
12
#4
0!
1)
1,
0+
1(
0'
02
01
10
#5
0,
1+
0)
12
#6
1!
1)
1,
0(
02
11
#7
0)
12
#8
1!
1)
1(
1.
1-
1'
0"
02
01
00
1/
#9
0!
0-
0)
12
#10
1!
1)
1-
0(
02
11
#11
0!
0.
0)
12
#12
1)
1$
0#
1(
1.
0'
02
01
10
#13
0$
1#
0)
12
#14
0%
1)
1$
0(
02
11
#15
0&
1%
0)
12
